rhea/__init__.py
rhea/agent/__init__.py
rhea/agent/schema.py
rhea/agent/tool.py
rhea/agent/utils.py
rhea/client/__init__.py
rhea/client/base.py
rhea/client/mcp.py
rhea/client/rest.py
rhea/manager/__init__.py
rhea/manager/launch_agent.py
rhea/manager/parsl_config.py
rhea/manager/run.py
rhea/manager/run_test.py
rhea/manager/utils.py
rhea/preprocess/__init__.py
rhea/preprocess/update_tools.py
rhea/preprocess/utils/fetch.py
rhea/preprocess/utils/process_xml.py
rhea/server/__init__.py
rhea/server/client_manager.py
rhea/server/mcp_server.py
rhea/server/metrics.py
rhea/server/rhea_fastmcp.py
rhea/server/schema.py
rhea/server/utils.py
rhea/utils/__init__.py
rhea/utils/embedding.py
rhea/utils/from_pickle.py
rhea/utils/models.py
rhea/utils/process.py
rhea/utils/proxy.py
rhea/utils/schema.py
rhea_mcp-0.1.1b5.dist-info/METADATA
rhea_mcp-0.1.1b5.dist-info/WHEEL
rhea_mcp-0.1.1b5.dist-info/top_level.txt
rhea_mcp-0.1.1b5.dist-info/RECORD
