Metadata-Version: 2.4
Name: rhea-mcp
Version: 0.1.1b5
Summary: A scalable MCP (Model Context Protocol) tool framework to serve thousands of biomedical tools for Large Language Models.
Requires-Python: >=3.10
Requires-Dist: academy-py>=0.2.0
Requires-Dist: asyncpg>=0.30.0
Requires-Dist: black>=25.1.0
Requires-Dist: cachetools>=6.1.0
Requires-Dist: cheetah3>=3.2.6.post1
Requires-Dist: conda-pack>=0.8.1
Requires-Dist: coverage[toml]>=7.9.1
Requires-Dist: debugpy>=1.8.14
Requires-Dist: fastapi[standard]>=0.115.14
Requires-Dist: filetype>=1.2.0
Requires-Dist: genbadge[all]>=1.1.2
Requires-Dist: greenlet>=3.2.3
Requires-Dist: griffe-inherited-docstrings>=1.1.1
Requires-Dist: kubernetes>=33.1.0
Requires-Dist: matplotlib>=3.10.5
Requires-Dist: mcp[cli]>=1.10.1
Requires-Dist: minio>=7.2.15
Requires-Dist: mkdocs>=1.6.1
Requires-Dist: mkdocs-autorefs>=1.4.2
Requires-Dist: mkdocs-material>=9.6.17
Requires-Dist: mkdocs-mermaid2-plugin>=1.2.1
Requires-Dist: mkdocstrings[python]>=0.30.0
Requires-Dist: mypy>=1.16.1
Requires-Dist: openai>=1.93.0
Requires-Dist: parsl>=2025.6.23
Requires-Dist: pgvector>=0.4.1
Requires-Dist: prometheus-client>=0.22.1
Requires-Dist: proxystore[all]>=0.8.2
Requires-Dist: psycopg2-binary>=2.9.10
Requires-Dist: pymdown-extensions>=10.16.1
Requires-Dist: pyright>=1.1.403
Requires-Dist: pytest>=8.4.1
Requires-Dist: pytest-asyncio>=1.0.0
Requires-Dist: pytest-cov>=6.2.1
Requires-Dist: pytest-xdist>=3.8.0
Requires-Dist: python-magic>=0.4.27
Requires-Dist: requests>=2.32.4
Requires-Dist: shellcheck-py>=0.10.0.1
Requires-Dist: sqlalchemy>=2.0.41
Requires-Dist: tqdm>=4.67.1
Requires-Dist: trio>=0.30.0
Requires-Dist: zstandard>=0.23.0
